communica/__init__.py
communica/clients.py
communica/exceptions.py
communica/servers.py
communica/connectors/__init__.py
communica/connectors/base.py
communica/connectors/dummy.py
communica/connectors/rabbitmq/__init__.py
communica/connectors/rabbitmq/connector.py
communica/connectors/rabbitmq/pool.py
communica/connectors/stream/__init__.py
communica/connectors/stream/connector.py
communica/connectors/stream/local_connections.py
communica/entities/__init__.py
communica/entities/base.py
communica/entities/route.py
communica/entities/simple.py
communica/serializers/__init__.py
communica/serializers/adaptix.py
communica/serializers/base.py
communica/serializers/json.py
communica/serializers/msgpack.py
communica/utils/__init__.py
communica/utils/delayer.py
communica/utils/unsorted.py
communica-0.4.3.dist-info/licenses/LICENSE.txt
communica-0.4.3.dist-info/METADATA
communica-0.4.3.dist-info/WHEEL
communica-0.4.3.dist-info/top_level.txt
communica-0.4.3.dist-info/RECORD
