Metadata-Version: 2.4
Name: communica
Version: 0.4.3
Summary: Easy to use IPC library
Author-email: Elchin Sarkarov <elchin751@gmail.com>
License-Expression: Apache-2.0
Project-URL: Homepage, https://github.com/Elchinchel/communica
Project-URL: Bug Tracker, https://github.com/Elchinchel/communica/issues
Classifier: Development Status :: 4 - Beta
Classifier: Programming Language :: Python :: 3
Classifier: Operating System :: POSIX
Classifier: Operating System :: Microsoft :: Windows
Requires-Python: >=3.9
License-File: LICENSE.txt
Requires-Dist: typing-extensions
Provides-Extra: orjson
Requires-Dist: orjson; extra == "orjson"
Provides-Extra: adaptix
Requires-Dist: adaptix; extra == "adaptix"
Provides-Extra: msgpack
Requires-Dist: msgpack; extra == "msgpack"
Provides-Extra: rabbitmq
Requires-Dist: aiormq; extra == "rabbitmq"
Requires-Dist: yarl; extra == "rabbitmq"
Dynamic: license-file
